Python/__init__.py
PyQwidgets-5.0.dist-info/METADATA
PyQwidgets-5.0.dist-info/WHEEL
PyQwidgets-5.0.dist-info/top_level.txt
PyQwidgets-5.0.dist-info/RECORD
