Metadata-Version: 2.1
Name: PyQwidgets
Version: 5.0
Summary: Уневерсальный модуль!
Author: Georg8528
Author-email: zadvornow2908@gmail.com
Classifier: Programming Language :: Python :: 3
Classifier: License :: OSI Approved :: MIT License
Classifier: Operating System :: OS Independent
Requires-Python: >=3.6
